[
    {
        "name": "Pink Party Strawberry Cake",
        "href": "recipe.html",
        "image": "pink_champagne_cake.jpg",
        "difficulty": 5,
        "category": "cake",
        "groups": "all low_sugar",
        "date": "30/06/2018"
    },
    {
        "name": "Kit-Kat Cake",
        "href": "recipe.html",
        "image": "kitkat_cake.jpg",
        "difficulty": 4,
        "category": "cake",
        "groups": "all low_calorie",
        "date": "30/06/2020"
    },
    {
        "name": "Strawberry Cake",
        "href": "recipe.html",
        "image": "strawberryCake.jpg",
        "difficulty": 3,
        "category": "cake",
        "groups": "all gluten_free",
        "date": "30/06/2015"
    },
    {
        "name": "Chocolate Cup Cake",
        "href": "recipe.html",
        "image": "cupcake.jpg",
        "difficulty": 1,
        "category": "cake",
        "groups": "all low_sugar",
        "date": "30/06/2011"
    },
    {
        "name": "Cheese Cake with Chocolate Base Cake",
        "href": "recipe.html",
        "image": "cheesecake1.jpg",
        "difficulty": 3,
        "category": "cake",
        "groups": "all vegan",
        "date": "30/06/2018"
    },
    {
        "name": "Carrot &amp; Walnut Cake",
        "href": "recipe.html",
        "image": "carrotcake1.jpg",
        "difficulty": 4,
        "category": "cake",
        "groups": "all vegan",
        "date": "30/06/2010"
    },
    {
        "name": "Pistachio &amp; Hazelnut Cake",
        "href": "recipe.html",
        "image": "pistachio_hazelnut_cake.jpg",
        "difficulty": 5,
        "category": "cake",
        "groups": "all vegan",
        "date": "30/08/2014"
    },
    {
        "name": "Easy Pumpkin Cake Recipe",
        "href": "recipe.html",
        "image": "EasyPumpkinRecipe.jpg",
        "difficulty": 2,
        "category": "cake",
        "groups": "all gluten_free",
        "date": "30/06/2018"
    },
    {
        "name": "Baguette",
        "href": "recipe.html",
        "image": "bread1.jpg",
        "difficulty": 3,
        "category": "bread",
        "groups": "all gluten_free",
        "date": "30/06/2008"
    },
    {
        "name": "Wheat Bread",
        "href": "recipe.html",
        "image": "WheatBread.jpg",
        "difficulty": 3,
        "category": "bread",
        "groups": "all gluten_free",
        "date": "30/06/2013"
    },
    {
        "name": "Whole Grain Bread",
        "href": "recipe.html",
        "image": "WholeGrainBread.jpg",
        "difficulty": 1,
        "category": "bread",
        "groups": "all gluten_free",
        "date": "30/06/2018"
    },
    {
        "name": "Cinnamon Raisin Bread",
        "href": "recipe.html",
        "image": "CinnamonRaisinBread.jpg",
        "difficulty": 4,
        "category": "bread",
        "groups": "all low_calorie",
        "date": "30/06/2005"
    },
    {
        "name": "Apple Cinnamon Bread",
        "href": "recipe.html",
        "image": "AppleCinnamonBread.jpg",
        "difficulty": 3,
        "category": "bread",
        "groups": "all low_calorie",
        "date": "30/06/2019"
    },
    {
        "name": "Croissant",
        "href": "recipe.html",
        "image": "croissant.jpg",
        "difficulty": 3,
        "category": "bread",
        "groups": "all vegan",
        "date": "30/06/2020"
    },
    {
        "name": "Walnut Cranberry Bread",
        "href": "recipe.html",
        "image": "walnutCramberryBread.jpg",
        "difficulty": 4,
        "category": "bread",
        "groups": "all vegan",
        "date": "30/06/2011"
    },
    {
        "name": "Chocolatine",
        "href": "recipe.html",
        "image": "chocolatine.jpg",
        "difficulty": 4,
        "category": "bread",
        "groups": "all vegan",
        "date": "30/06/2017"
    },
    {
        "name": "Chocolate Chip Cookies",
        "href": "recipe.html",
        "image": "chocolateChipCookies.jpg",
        "difficulty": 1,
        "category": "cookies",
        "groups": "all vegan",
        "date": "30/06/2009"
    },
    {
        "name": "Red Velvet Cookie",
        "href": "recipe.html",
        "image": "RedVelvetCookie.jpg",
        "difficulty": 2,
        "category": "cookies",
        "groups": "all low_calorie",
        "date": "30/06/2013"
    },
    {
        "name": "Diet Cookie",
        "href": "recipe.html",
        "image": "DietCookie.jpg",
        "difficulty": 5,
        "category": "cookies",
        "groups": "all gluten_free",
        "date": "30/06/2017"
    },
    {
        "name": "Sweet Fruit Pie Cookie",
        "href": "recipe.html",
        "image": "SweetFruitPieCookie.jpg",
        "difficulty": 4,
        "category": "cookies",
        "groups": "all low_calorie",
        "date": "30/06/2020"
    },
    {
        "name": "Berries Pie",
        "href": "recipe.html",
        "image": "mix_berries_pie2.jpg",
        "difficulty": 2,
        "category": "pie",
        "groups": "all low_calorie",
        "date": "30/06/2013"
    },
    {
        "name": "Strawberry pie",
        "href": "recipe.html",
        "image": "strawberry.jpg",
        "difficulty": 1,
        "category": "pie",
        "groups": "all low_sugar",
        "date": "10/11/2015"
    },
    {
        "name": "Apple Pie",
        "href": "recipe.html",
        "image": "apple_pie2.jpg",
        "difficulty": 0,
        "category": "pie",
        "groups": "all gluten_free",
        "date": "30/09/2015"
    },
    {
        "name": "Walnut Pie",
        "href": "recipe.html",
        "image": "walnut.jpg",
        "difficulty": 4,
        "category": "pie",
        "groups": "all vegan",
        "date": "30/06/2014"
    },
    {
        "name": "Blackberry Pie",
        "href": "recipe.html",
        "image": "BlackberryPie.jpg",
        "difficulty": 3,
        "category": "pie",
        "groups": "all vegan",
        "date": "30/06/2009"
    },
    {
        "name": "Plum Pie",
        "href": "recipe.html",
        "image": "plumPie.jpg",
        "difficulty": 2,
        "category": "pie",
        "groups": "all low_calorie",
        "date": ""
    },
    {
        "name": "Special Strawberry Pie",
        "href": "recipe.html",
        "image": "strawberry-pie-recipe-8.jpg",
        "difficulty": 5,
        "category": "pie",
        "groups": "all low_sugr",
        "date": "30/06/2010"
    },
    {
        "name": "Berries Pie",
        "href": "recipe.html",
        "image": "mix_berries.jpg",
        "difficulty": 4,
        "category": "pie",
        "groups": "all gluten_free",
        "date": "30/06/2021"
    }
]